{
    "zone":[
        {
            "id" : 1,
            "name" : "Laureles"
        },
        {
            "id" : 2,
            "name" : "Belen"
        },
        {
            "id" : 3,
            "name" : "Poblado"
        },
        {
            "id" : 4,
            "name" : "Envigado"
        },
        {
            "id" : 5,
            "name" : "Sabaneta"
        }
    ],
    "property-type":[
        {
            "id" : 1,
            "name" : "Apartamento"
        },
        {
            "id" : 2,
            "name" : "Casa"
        }
    ],
    "PropertyObjective":[
        {
            "id" : 1,
            "name" : "Arrendamiento"
        },
        {
            "id" : 2,
            "name" : "Venta"
        }
    ],
    "Seller" :[],
    "Customer" :[],
    "Properties":[]
  }